music_mood_analysis/__init__.py
music_mood_analysis/__main__.py
music_mood_analysis/cli.py
music_mood_analysis/consts.py
music_mood_analysis/dataconversion.py
music_mood_analysis/math_util.py
music_mood_analysis/plots.py
music_mood_analysis/py.typed
music_mood_analysis/tempo.py
music_mood_analysis/tonality.py
music_mood_analysis/util.py
music_mood_analysis/gui/__init__.py
music_mood_analysis/gui/callbacks.py
music_mood_analysis/gui/components.py
music_mood_analysis/gui/config.py
music_mood_analysis/gui/figure.py
music_mood_analysis/gui/init.py
music_mood_analysis/gui/media/icon.png
music_mood_analysis-1.0.5.dist-info/LICENSE
music_mood_analysis-1.0.5.dist-info/METADATA
music_mood_analysis-1.0.5.dist-info/WHEEL
music_mood_analysis-1.0.5.dist-info/top_level.txt
music_mood_analysis-1.0.5.dist-info/RECORD
