Metadata-Version: 2.1
Name: music_mood_analysis
Version: 1.0.5
Summary: Music mood analysis
Home-page: https://github.com/rbaltrusch/music_mood_analysis
Author: Richard Baltrusch
License: AGPLv3
Keywords: python
Classifier: Development Status :: 4 - Beta
Classifier: Environment :: Console
Classifier: Intended Audience :: Developers
Classifier: Intended Audience :: End Users/Desktop
Classifier: Intended Audience :: Science/Research
Classifier: License :: OSI Approved :: GNU Affero General Public License v3 or later (AGPLv3+)
Classifier: Programming Language :: Python
Classifier: Programming Language :: Python :: 3
Classifier: Programming Language :: Python :: 3 :: Only
Classifier: Programming Language :: Python :: 3.8
Classifier: Programming Language :: Python :: 3.9
Classifier: Programming Language :: Python :: 3.10
Classifier: Programming Language :: Python :: 3.11
Classifier: Topic :: Artistic Software
Classifier: Topic :: Desktop Environment
Classifier: Topic :: Multimedia
Classifier: Topic :: Multimedia :: Sound/Audio
Classifier: Topic :: Multimedia :: Sound/Audio :: Analysis
Classifier: Topic :: Scientific/Engineering
Classifier: Typing :: Typed
Requires-Python: >=3.8
License-File: LICENSE
Requires-Dist: matplotlib ==3.7.0
Requires-Dist: numpy ==1.24.0
Requires-Dist: scipy ==1.10.1 ; python_version < "3.9"
Requires-Dist: scipy ==1.13.0 ; python_version >= "3.9"
